xsdata_ech/__init__.py
xsdata_ech/e_ch_0006_2_0.py
xsdata_ech/e_ch_0007_6_0.py
xsdata_ech/e_ch_0008_3_0.py
xsdata_ech/e_ch_0010_6_0.py
xsdata_ech/e_ch_0044_4_1.py
xsdata_ech/e_ch_0058_5_0.py
xsdata_ech/e_ch_0155_5_0.py
xsdata_ech/e_ch_0157_5_0.py
xsdata_ech/e_ch_0159_5_0.py
xsdata_ech/e_ch_0252_1_0.py
xsdata_ech/e_ch_0252_2_0.py
xsdata_ech/py.typed
xsdata_ech-0.3.0.dist-info/LICENSE
xsdata_ech-0.3.0.dist-info/METADATA
xsdata_ech-0.3.0.dist-info/WHEEL
xsdata_ech-0.3.0.dist-info/top_level.txt
xsdata_ech-0.3.0.dist-info/RECORD
