Metadata-Version: 2.1
Name: xsdata-ech
Version: 0.3.0
Summary: eCH xsdata dataclasses
Home-page: https://github.com/seantis/xsdata-ech
Author: Seantis GmbH
Author-email: info@seantis.ch
License: MIT
Project-URL: Bug Tracker, https://github.com/seantis/xsdata-ech/issues
Classifier: Development Status :: 4 - Beta
Classifier: License :: OSI Approved :: MIT License
Classifier: Programming Language :: Python
Classifier: Programming Language :: Python :: 3.8
Classifier: Programming Language :: Python :: 3.9
Classifier: Programming Language :: Python :: 3.10
Classifier: Programming Language :: Python :: 3.11
Classifier: Programming Language :: Python :: 3.12
Classifier: Programming Language :: Python :: 3.13
Classifier: Programming Language :: Python :: Implementation :: CPython
Classifier: License :: OSI Approved :: MIT License
Requires-Python: >=3.8
License-File: LICENSE
Requires-Dist: xsdata
Provides-Extra: dev
Requires-Dist: pre-commit; extra == "dev"
Requires-Dist: bump2version; extra == "dev"
Requires-Dist: xsdata[cli]; extra == "dev"
Provides-Extra: test
Requires-Dist: bandit[toml]; extra == "test"
Requires-Dist: flake8; extra == "test"
Requires-Dist: flake8-bugbear; extra == "test"
Requires-Dist: flake8-pyi; extra == "test"
Requires-Dist: mypy; extra == "test"
Requires-Dist: pytest; extra == "test"
Requires-Dist: tox; extra == "test"
